garages_amsterdam/__init__.py
garages_amsterdam/const.py
garages_amsterdam/exceptions.py
garages_amsterdam/garages_amsterdam.py
garages_amsterdam/models.py
garages_amsterdam/py.typed
garages_amsterdam-4.1.0.dist-info/LICENSE
garages_amsterdam-4.1.0.dist-info/WHEEL
garages_amsterdam-4.1.0.dist-info/METADATA
garages_amsterdam-4.1.0.dist-info/RECORD
