Metadata-Version: 2.1
Name: garages-amsterdam
Version: 4.1.0
Summary: Asynchronous Python client for the Garages Amsterdam
Home-page: https://github.com/klaasnicolaas/python-garages-amsterdam
License: MIT
Keywords: garages,amsterdam,car,occupancy,async,client
Author: Klaas Schoute
Author-email: hello@student-techlife.com
Maintainer: Klaas Schoute
Maintainer-email: hello@student-techlife.com
Requires-Python: >=3.9,<4.0
Classifier: Framework :: AsyncIO
Classifier: Intended Audience :: Developers
Classifier: License :: OSI Approved :: MIT License
Classifier: Natural Language :: English
Classifier: Programming Language :: Python :: 3
Classifier: Programming Language :: Python :: 3.10
Classifier: Programming Language :: Python :: 3.9
Classifier: Topic :: Software Development :: Libraries :: Python Modules
Requires-Dist: aiohttp (>=3.0.0)
Requires-Dist: yarl (>=1.6.0)
Project-URL: Bug Tracker, https://github.com/klaasnicolaas/python-garages-amsterdam/issues
Project-URL: Changelog, https://github.com/klaasnicolaas/python-garages-amsterdam/releases
Project-URL: Documentation, https://github.com/klaasnicolaas/python-garages-amsterdam
Project-URL: Repository, https://github.com/klaasnicolaas/python-garages-amsterdam
